specs
RunnerBean
