Metadata-Version: 1.0
Name: RunnerBean
Version: 0.4.3-dev
Summary: A simple tool for creating long-running Python workers listening for Beanstalk jobs.
Home-page: https://github.com/wewriteapps/RunnerBean
Author: UNKNOWN
Author-email: UNKNOWN
License: UNKNOWN
Platform: UNKNOWN
